{
  "code_version": "1645f3589408503894c7e8f44a92ffe382a9a5b4+dirty",
  "complete": true,
  "discount_rate": 0.02417932519702056,
  "draw": 8,
  "horizon_days": 2000,
  "regimes": [
    "current_eu_supervision",
    "sme_algorithmic_prescreening",
    "certified_green_data_connector"
  ],
  "replications": 3,
  "rows": [
    {
      "market_seed": 28260716,
      "metrics": {
        "backlog_pending_cases": 583.0,
        "bank_benefit_misallocation": 0.0,
        "benefit_before_detection": 97391.61722952453,
        "calculation_greenwashing": 481.0,
        "case_completion_days_mean": 266.51147540983607,
        "conflict_cases_opened": 8.0,
        "conflict_claim_corrected": 0.0,
        "conflict_confirmed_firm_claim": 0.0,
        "conflict_dismissed_unresolved": 0.0,
        "conflict_escalated_corroborated": 2.0,
        "conflict_investigations": 8.0,
        "conflict_pending_unresolved": 0.0,
        "conflict_register_corrected": 6.0,
        "conflict_resolution_delay_mean": 51.0,
        "connector_active_source_share": 0.0,
        "consumer_exposure": 1306.0,
        "consumer_perceived_misallocation": 0.10673827382142441,
        "corrected_material_claims": 31.0,
        "correction_delay_days": 355.17543859649123,
        "cost_per_detected_material_claim": 237.49674054758802,
        "cost_per_prevented_material_claim": 0.0,
        "detection_coverage": 0.3934077618288145,
        "detection_delay_days": 0.13298565840938723,
        "discount_rate_annual": 0.02417932519702056,
        "discounted_exposure_weighted_severity": 234457.06762289687,
        "discounted_total_public_cost": 170877.25384803547,
        "employee_trust_mean": 0.4369318148284666,
        "evidence_quality_mean": 0.2133422134921272,
        "exposure_weighted_severity": 246173.21506368005,
        "false_negatives": 87.0,
        "false_positive_rate_assessed": 0.0,
        "false_positives": 0.0,
        "firm_policy_cost": 0.0,
        "firm_reporting_cost": 6318.233140067017,
        "foregone_consumer_premium": 0.0,
        "green_welfare_share": 0.23930525454124255,
        "gross_emissions_final": 4055384.1225517555,
        "hub_participation_rate": 0.0,
        "hub_tot_meaningful_revision_rate": 0.0,
        "hub_tot_revision_rate_adaptive": 0.0,
        "hub_tot_revision_rate_greenwasher": 0.0,
        "hub_tot_revision_rate_honest": 0.0,
        "investor_exposure": 1283.0,
        "investor_signal_distortion": 0.12263720929319484,
        "live_uncorrected_material_overstatements": 1872.0,
        "manual_overrides": 0.0,
        "mean_days_to_correction": 355.17543859649123,
        "mean_greenhushing_gap": 0.0,
        "mean_reporting_delay_days": 0.0,
        "misleading_claim_days": 1662375.0,
        "noise_only_overstatements": 623.0,
        "original_material_overstatements": 1881.0,
        "population_detection_recall": 0.34821903242955876,
        "precision": 1.0,
        "prepublication_meaningful_revisions": 0.0,
        "prepublication_noise_flag_share": 0.0,
        "prepublication_revisions": 0.0,
        "prepublication_withheld_overstatements": 0.0,
        "privacy_cyber_incidents": 0.0,
        "published_claims": 2618.0,
        "queue_mean_age_days": 825.008576329331,
        "queue_tail_age_days_p90": 1760.0,
        "real_environmental_investment": 277843.94948354963,
        "recall": 0.8981264637002342,
        "recurrence_after_feedback": 0.0,
        "regulator_time_cost": 182160.0,
        "repeated_abuse_firms": 10.0,
        "screening_conditioned_precision": 1.0,
        "screening_conditioned_recall": 0.8981264637002342,
        "severity_weighted_detection_recall": 0.5105391151683215,
        "severity_weighted_greenwashing": 271.02406371975866,
        "sme_burden": 2640.912836236261,
        "specificity": 1.0,
        "state_policy_cost": 0.0,
        "strategic_material_overstatements": 1258.0,
        "strategic_share_of_material": 0.6687931951089846,
        "subsidy_misallocation": 147164.50153443846,
        "time_to_correction_mean": 5.0,
        "true_material_overstatements": 1881.0,
        "true_negatives": 36.0,
        "true_positives": 767.0,
        "turnover_replacement_cost": 4948516.643741734,
        "uncommunicated_real_performance": 0.0,
        "unresolved_uncertainty": 59.0,
        "unsupported_generic_claims": 436.0,
        "voluntary_claims_published": 1592.0,
        "voluntary_reporting_declines": 0.0,
        "withheld_truthful_claims": 0.0
      },
      "regime": "current_eu_supervision",
      "replication": 0,
      "supervision_seed": 942561
    },
    {
      "market_seed": 28260716,
      "metrics": {
        "backlog_pending_cases": 570.0,
        "bank_benefit_misallocation": 0.0,
        "benefit_before_detection": 98229.81851451816,
        "calculation_greenwashing": 481.0,
        "case_completion_days_mean": 257.2987421383648,
        "conflict_cases_opened": 7.0,
        "conflict_claim_corrected": 0.0,
        "conflict_confirmed_firm_claim": 0.0,
        "conflict_dismissed_unresolved": 0.0,
        "conflict_escalated_corroborated": 1.0,
        "conflict_investigations": 7.0,
        "conflict_pending_unresolved": 0.0,
        "conflict_register_corrected": 6.0,
        "conflict_resolution_delay_mean": 51.0,
        "connector_active_source_share": 0.0,
        "consumer_exposure": 1291.0,
        "consumer_perceived_misallocation": 0.10207228514976557,
        "corrected_material_claims": 22.0,
        "correction_delay_days": 357.5219298245614,
        "cost_per_detected_material_claim": 281.2599469496021,
        "cost_per_prevented_material_claim": 416.3888888888889,
        "detection_coverage": 0.3962162162162162,
        "detection_delay_days": 1.3390728476821192,
        "discount_rate_annual": 0.02417932519702056,
        "discounted_exposure_weighted_severity": 229407.7897059023,
        "discounted_total_public_cost": 200351.13363826467,
        "employee_trust_mean": 0.44534322861089515,
        "evidence_quality_mean": 0.21334344964948948,
        "exposure_weighted_severity": 240921.94927253836,
        "false_negatives": 92.0,
        "false_positive_rate_assessed": 0.023255813953488372,
        "false_positives": 1.0,
        "firm_policy_cost": 7715.0,
        "firm_reporting_cost": 6296.724429485823,
        "foregone_consumer_premium": 1915.6357618327936,
        "green_welfare_share": 0.23223225541181441,
        "gross_emissions_final": 4080953.7689895746,
        "hub_participation_rate": 0.2361111111111111,
        "hub_tot_meaningful_revision_rate": 0.6638655462184874,
        "hub_tot_revision_rate_adaptive": 0.6785714285714286,
        "hub_tot_revision_rate_greenwasher": 0.19047619047619047,
        "hub_tot_revision_rate_honest": 0.8,
        "investor_exposure": 1267.0,
        "investor_signal_distortion": 0.12678872231848737,
        "live_uncorrected_material_overstatements": 1845.0,
        "manual_overrides": 0.0,
        "mean_days_to_correction": 357.5219298245614,
        "mean_greenhushing_gap": 0.0038312715236655873,
        "mean_reporting_delay_days": 4.0,
        "misleading_claim_days": 1641970.0,
        "noise_only_overstatements": 618.0,
        "original_material_overstatements": 1850.0,
        "population_detection_recall": 0.34702702702702704,
        "precision": 0.9986754966887417,
        "prepublication_meaningful_revisions": 79.0,
        "prepublication_noise_flag_share": 0.0,
        "prepublication_revisions": 79.0,
        "prepublication_withheld_overstatements": 11.0,
        "privacy_cyber_incidents": 0.0,
        "published_claims": 2602.0,
        "queue_mean_age_days": 814.2105263157895,
        "queue_tail_age_days_p90": 1640.0,
        "real_environmental_investment": 275114.0122007468,
        "recall": 0.8912529550827423,
        "recurrence_after_feedback": 246.0,
        "regulator_time_cost": 182310.0,
        "repeated_abuse_firms": 10.0,
        "screening_conditioned_precision": 0.9986754966887417,
        "screening_conditioned_recall": 0.8912529550827423,
        "severity_weighted_detection_recall": 0.510285382945274,
        "severity_weighted_greenwashing": 264.9912177649564,
        "sme_burden": 10347.699893865723,
        "specificity": 0.9767441860465116,
        "state_policy_cost": 29760.0,
        "strategic_material_overstatements": 1232.0,
        "strategic_share_of_material": 0.6659459459459459,
        "subsidy_misallocation": 152146.314635718,
        "time_to_correction_mean": 5.0,
        "true_material_overstatements": 1850.0,
        "true_negatives": 42.0,
        "true_positives": 754.0,
        "turnover_replacement_cost": 4994563.245993546,
        "uncommunicated_real_performance": 0.0038312715236655873,
        "unresolved_uncertainty": 66.0,
        "unsupported_generic_claims": 407.0,
        "voluntary_claims_published": 1576.0,
        "voluntary_reporting_declines": 55.0,
        "withheld_truthful_claims": 4.0
      },
      "regime": "sme_algorithmic_prescreening",
      "replication": 0,
      "supervision_seed": 942561
    },
    {
      "market_seed": 28260716,
      "metrics": {
        "backlog_pending_cases": 589.0,
        "bank_benefit_misallocation": 0.0,
        "benefit_before_detection": 103630.32584443853,
        "calculation_greenwashing": 362.0,
        "case_completion_days_mean": 228.87290969899666,
        "conflict_cases_opened": 13.0,
        "conflict_claim_corrected": 0.0,
        "conflict_confirmed_firm_claim": 0.0,
        "conflict_dismissed_unresolved": 3.0,
        "conflict_escalated_corroborated": 3.0,
        "conflict_investigations": 13.0,
        "conflict_pending_unresolved": 1.0,
        "conflict_register_corrected": 6.0,
        "conflict_resolution_delay_mean": 60.083333333333336,
        "connector_active_source_share": 0.6625,
        "consumer_exposure": 1168.0,
        "consumer_perceived_misallocation": 0.0798562875007908,
        "corrected_material_claims": 25.0,
        "correction_delay_days": 305.8333333333333,
        "cost_per_detected_material_claim": 391.8872870249017,
        "cost_per_prevented_material_claim": 119100.0,
        "detection_coverage": 0.4191651969429747,
        "detection_delay_days": 0.23859191655801826,
        "discount_rate_annual": 0.02417932519702056,
        "discounted_exposure_weighted_severity": 217691.11132280974,
        "discounted_total_public_cost": 283953.02230633836,
        "employee_trust_mean": 0.4730867066050372,
        "evidence_quality_mean": 0.2133452108082996,
        "exposure_weighted_severity": 228339.07594633903,
        "false_negatives": 80.0,
        "false_positive_rate_assessed": 0.08333333333333333,
        "false_positives": 4.0,
        "firm_policy_cost": 1500.0,
        "firm_reporting_cost": 6269.149587869693,
        "foregone_consumer_premium": 0.0,
        "green_welfare_share": 0.23330566178391693,
        "gross_emissions_final": 4076995.2754197875,
        "hub_participation_rate": 0.0,
        "hub_tot_meaningful_revision_rate": 0.0,
        "hub_tot_revision_rate_adaptive": 0.0,
        "hub_tot_revision_rate_greenwasher": 0.0,
        "hub_tot_revision_rate_honest": 0.0,
        "investor_exposure": 1122.0,
        "investor_signal_distortion": 0.12914749932097339,
        "live_uncorrected_material_overstatements": 1692.0,
        "manual_overrides": 57.0,
        "mean_days_to_correction": 305.8333333333333,
        "mean_greenhushing_gap": 0.0,
        "mean_reporting_delay_days": 0.0,
        "misleading_claim_days": 1535085.0,
        "noise_only_overstatements": 564.0,
        "original_material_overstatements": 1701.0,
        "population_detection_recall": 0.37389770723104054,
        "precision": 0.9947848761408083,
        "prepublication_meaningful_revisions": 0.0,
        "prepublication_noise_flag_share": 0.0,
        "prepublication_revisions": 0.0,
        "prepublication_withheld_overstatements": 0.0,
        "privacy_cyber_incidents": 10.8,
        "published_claims": 2604.0,
        "queue_mean_age_days": 845.2292020373515,
        "queue_tail_age_days_p90": 1760.0,
        "real_environmental_investment": 283547.944564321,
        "recall": 0.9051008303677343,
        "recurrence_after_feedback": 0.0,
        "regulator_time_cost": 181410.0,
        "repeated_abuse_firms": 10.0,
        "screening_conditioned_precision": 0.9947848761408083,
        "screening_conditioned_recall": 0.9051008303677343,
        "severity_weighted_detection_recall": 0.5373428902573791,
        "severity_weighted_greenwashing": 247.4357804773637,
        "sme_burden": 3211.2744835095764,
        "specificity": 0.9166666666666666,
        "state_policy_cost": 117600.0,
        "strategic_material_overstatements": 1137.0,
        "strategic_share_of_material": 0.6684303350970018,
        "subsidy_misallocation": 154976.8480825938,
        "time_to_correction_mean": 5.0,
        "true_material_overstatements": 1701.0,
        "true_negatives": 44.0,
        "true_positives": 763.0,
        "turnover_replacement_cost": 4768502.870038156,
        "uncommunicated_real_performance": 0.0,
        "unresolved_uncertainty": 53.0,
        "unsupported_generic_claims": 421.0,
        "voluntary_claims_published": 1578.0,
        "voluntary_reporting_declines": 0.0,
        "withheld_truthful_claims": 0.0
      },
      "regime": "certified_green_data_connector",
      "replication": 0,
      "supervision_seed": 942561
    },
    {
      "market_seed": 28261716,
      "metrics": {
        "backlog_pending_cases": 576.0,
        "bank_benefit_misallocation": 0.0,
        "benefit_before_detection": 108372.81480721514,
        "calculation_greenwashing": 490.0,
        "case_completion_days_mean": 266.8525641025641,
        "conflict_cases_opened": 3.0,
        "conflict_claim_corrected": 0.0,
        "conflict_confirmed_firm_claim": 0.0,
        "conflict_dismissed_unresolved": 0.0,
        "conflict_escalated_corroborated": 0.0,
        "conflict_investigations": 3.0,
        "conflict_pending_unresolved": 0.0,
        "conflict_register_corrected": 3.0,
        "conflict_resolution_delay_mean": 51.0,
        "connector_active_source_share": 0.0,
        "consumer_exposure": 1303.0,
        "consumer_perceived_misallocation": 0.10239913688569897,
        "corrected_material_claims": 29.0,
        "correction_delay_days": 349.1806722689076,
        "cost_per_detected_material_claim": 239.72477064220183,
        "cost_per_prevented_material_claim": 0.0,
        "detection_coverage": 0.3847791378392762,
        "detection_delay_days": 0.0,
        "discount_rate_annual": 0.02417932519702056,
        "discounted_exposure_weighted_severity": 232343.4794425173,
        "discounted_total_public_cost": 171561.87042418148,
        "employee_trust_mean": 0.4357924378411916,
        "evidence_quality_mean": 0.21331446248780106,
        "exposure_weighted_severity": 244085.59237127338,
        "false_negatives": 84.0,
        "false_positive_rate_assessed": 0.04878048780487805,
        "false_positives": 2.0,
        "firm_policy_cost": 0.0,
        "firm_reporting_cost": 6313.83935252811,
        "foregone_consumer_premium": 0.0,
        "green_welfare_share": 0.261976755900052,
        "gross_emissions_final": 3993424.795477923,
        "hub_participation_rate": 0.0,
        "hub_tot_meaningful_revision_rate": 0.0,
        "hub_tot_revision_rate_adaptive": 0.0,
        "hub_tot_revision_rate_greenwasher": 0.0,
        "hub_tot_revision_rate_honest": 0.0,
        "investor_exposure": 1309.0,
        "investor_signal_distortion": 0.12371847809358043,
        "live_uncorrected_material_overstatements": 1876.0,
        "manual_overrides": 0.0,
        "mean_days_to_correction": 349.1806722689076,
        "mean_greenhushing_gap": 0.0,
        "mean_reporting_delay_days": 0.0,
        "misleading_claim_days": 1666805.0,
        "noise_only_overstatements": 631.0,
        "original_material_overstatements": 1879.0,
        "population_detection_recall": 0.3400745077168707,
        "precision": 0.9973856209150327,
        "prepublication_meaningful_revisions": 0.0,
        "prepublication_noise_flag_share": 0.0,
        "prepublication_revisions": 0.0,
        "prepublication_withheld_overstatements": 0.0,
        "privacy_cyber_incidents": 0.0,
        "published_claims": 2609.0,
        "queue_mean_age_days": 827.2916666666666,
        "queue_tail_age_days_p90": 1760.0,
        "real_environmental_investment": 288724.57793017477,
        "recall": 0.9008264462809917,
        "recurrence_after_feedback": 0.0,
        "regulator_time_cost": 182910.0,
        "repeated_abuse_firms": 10.0,
        "screening_conditioned_precision": 0.9973856209150327,
        "screening_conditioned_recall": 0.9008264462809917,
        "severity_weighted_detection_recall": 0.5086929928776365,
        "severity_weighted_greenwashing": 270.95721565627326,
        "sme_burden": 2628.0657125951802,
        "specificity": 0.9512195121951219,
        "state_policy_cost": 0.0,
        "strategic_material_overstatements": 1248.0,
        "strategic_share_of_material": 0.6641830761043108,
        "subsidy_misallocation": 148462.0289616771,
        "time_to_correction_mean": 5.0,
        "true_material_overstatements": 1879.0,
        "true_negatives": 39.0,
        "true_positives": 763.0,
        "turnover_replacement_cost": 4919914.427913828,
        "uncommunicated_real_performance": 0.0,
        "unresolved_uncertainty": 51.0,
        "unsupported_generic_claims": 439.0,
        "voluntary_claims_published": 1583.0,
        "voluntary_reporting_declines": 0.0,
        "withheld_truthful_claims": 0.0
      },
      "regime": "current_eu_supervision",
      "replication": 1,
      "supervision_seed": 950480
    },
    {
      "market_seed": 28261716,
      "metrics": {
        "backlog_pending_cases": 568.0,
        "bank_benefit_misallocation": 0.0,
        "benefit_before_detection": 110542.88047569898,
        "calculation_greenwashing": 490.0,
        "case_completion_days_mean": 243.240625,
        "conflict_cases_opened": 2.0,
        "conflict_claim_corrected": 0.0,
        "conflict_confirmed_firm_claim": 0.0,
        "conflict_dismissed_unresolved": 0.0,
        "conflict_escalated_corroborated": 0.0,
        "conflict_investigations": 2.0,
        "conflict_pending_unresolved": 0.0,
        "conflict_register_corrected": 2.0,
        "conflict_resolution_delay_mean": 51.0,
        "connector_active_source_share": 0.0,
        "consumer_exposure": 1288.0,
        "consumer_perceived_misallocation": 0.09878713566463032,
        "corrected_material_claims": 18.0,
        "correction_delay_days": 333.6266094420601,
        "cost_per_detected_material_claim": 281.8758256274769,
        "cost_per_prevented_material_claim": 409.6276595744681,
        "detection_coverage": 0.38461538461538464,
        "detection_delay_days": 2.216358839050132,
        "discount_rate_annual": 0.02417932519702056,
        "discounted_exposure_weighted_severity": 225107.23363533316,
        "discounted_total_public_cost": 201612.88192952675,
        "employee_trust_mean": 0.4454791915857643,
        "evidence_quality_mean": 0.21331609203849394,
        "exposure_weighted_severity": 236530.6675712397,
        "false_negatives": 72.0,
        "false_positive_rate_assessed": 0.01694915254237288,
        "false_positives": 1.0,
        "firm_policy_cost": 8185.0,
        "firm_reporting_cost": 6277.106439603049,
        "foregone_consumer_premium": 1809.216404857242,
        "green_welfare_share": 0.2437805670092674,
        "gross_emissions_final": 4051550.3007524633,
        "hub_participation_rate": 0.2638888888888889,
        "hub_tot_meaningful_revision_rate": 0.6090225563909775,
        "hub_tot_revision_rate_adaptive": 0.5714285714285714,
        "hub_tot_revision_rate_greenwasher": 0.2857142857142857,
        "hub_tot_revision_rate_honest": 0.8392857142857143,
        "investor_exposure": 1291.0,
        "investor_signal_distortion": 0.12801349441869442,
        "live_uncorrected_material_overstatements": 1842.0,
        "manual_overrides": 0.0,
        "mean_days_to_correction": 333.6266094420601,
        "mean_greenhushing_gap": 0.003618432809714484,
        "mean_reporting_delay_days": 4.0,
        "misleading_claim_days": 1650410.0,
        "noise_only_overstatements": 628.0,
        "original_material_overstatements": 1846.0,
        "population_detection_recall": 0.3456121343445287,
        "precision": 0.9986807387862797,
        "prepublication_meaningful_revisions": 81.0,
        "prepublication_noise_flag_share": 0.0,
        "prepublication_revisions": 81.0,
        "prepublication_withheld_overstatements": 13.0,
        "privacy_cyber_incidents": 0.0,
        "published_claims": 2595.0,
        "queue_mean_age_days": 837.6056338028169,
        "queue_tail_age_days_p90": 1760.0,
        "real_environmental_investment": 292234.2913844662,
        "recall": 0.9131483715319663,
        "recurrence_after_feedback": 290.0,
        "regulator_time_cost": 183060.0,
        "repeated_abuse_firms": 10.0,
        "screening_conditioned_precision": 0.9986807387862797,
        "screening_conditioned_recall": 0.9131483715319663,
        "severity_weighted_detection_recall": 0.5132195331097817,
        "severity_weighted_greenwashing": 262.47066932152495,
        "sme_burden": 10808.988572465692,
        "specificity": 0.9830508474576272,
        "state_policy_cost": 30320.0,
        "strategic_material_overstatements": 1218.0,
        "strategic_share_of_material": 0.6598049837486457,
        "subsidy_misallocation": 153616.0422465098,
        "time_to_correction_mean": 11.666666666666666,
        "true_material_overstatements": 1846.0,
        "true_negatives": 58.0,
        "true_positives": 757.0,
        "turnover_replacement_cost": 4938313.153202121,
        "uncommunicated_real_performance": 0.003618432809714484,
        "unresolved_uncertainty": 43.0,
        "unsupported_generic_claims": 417.0,
        "voluntary_claims_published": 1569.0,
        "voluntary_reporting_declines": 53.0,
        "withheld_truthful_claims": 5.0
      },
      "regime": "sme_algorithmic_prescreening",
      "replication": 1,
      "supervision_seed": 950480
    },
    {
      "market_seed": 28261716,
      "metrics": {
        "backlog_pending_cases": 578.0,
        "bank_benefit_misallocation": 0.0,
        "benefit_before_detection": 107422.97639267283,
        "calculation_greenwashing": 382.0,
        "case_completion_days_mean": 230.38709677419354,
        "conflict_cases_opened": 7.0,
        "conflict_claim_corrected": 1.0,
        "conflict_confirmed_firm_claim": 0.0,
        "conflict_dismissed_unresolved": 1.0,
        "conflict_escalated_corroborated": 1.0,
        "conflict_investigations": 7.0,
        "conflict_pending_unresolved": 0.0,
        "conflict_register_corrected": 4.0,
        "conflict_resolution_delay_mean": 65.14285714285714,
        "connector_active_source_share": 0.675,
        "consumer_exposure": 1193.0,
        "consumer_perceived_misallocation": 0.09357458850106318,
        "corrected_material_claims": 21.0,
        "correction_delay_days": 309.19565217391306,
        "cost_per_detected_material_claim": 393.5826771653543,
        "cost_per_prevented_material_claim": 119100.0,
        "detection_coverage": 0.41237113402061853,
        "detection_delay_days": 0.0799475753604194,
        "discount_rate_annual": 0.02417932519702056,
        "discounted_exposure_weighted_severity": 222811.78640116815,
        "discounted_total_public_cost": 284795.62135865755,
        "employee_trust_mean": 0.4059711636701513,
        "evidence_quality_mean": 0.21331560161076144,
        "exposure_weighted_severity": 233769.2278854712,
        "false_negatives": 79.0,
        "false_positive_rate_assessed": 0.020833333333333332,
        "false_positives": 1.0,
        "firm_policy_cost": 1500.0,
        "firm_reporting_cost": 6292.616161721888,
        "foregone_consumer_premium": 0.0,
        "green_welfare_share": 0.24672590422142934,
        "gross_emissions_final": 4040486.443629619,
        "hub_participation_rate": 0.0,
        "hub_tot_meaningful_revision_rate": 0.0,
        "hub_tot_revision_rate_adaptive": 0.0,
        "hub_tot_revision_rate_greenwasher": 0.0,
        "hub_tot_revision_rate_honest": 0.0,
        "investor_exposure": 1178.0,
        "investor_signal_distortion": 0.12749878353504046,
        "live_uncorrected_material_overstatements": 1741.0,
        "manual_overrides": 40.0,
        "mean_days_to_correction": 309.19565217391306,
        "mean_greenhushing_gap": 0.0,
        "mean_reporting_delay_days": 0.0,
        "misleading_claim_days": 1582755.0,
        "noise_only_overstatements": 578.0,
        "original_material_overstatements": 1746.0,
        "population_detection_recall": 0.36769759450171824,
        "precision": 0.9986893840104849,
        "prepublication_meaningful_revisions": 0.0,
        "prepublication_noise_flag_share": 0.0,
        "prepublication_revisions": 0.0,
        "prepublication_withheld_overstatements": 0.0,
        "privacy_cyber_incidents": 14.4,
        "published_claims": 2605.0,
        "queue_mean_age_days": 861.2456747404844,
        "queue_tail_age_days_p90": 1760.0,
        "real_environmental_investment": 275884.8190874987,
        "recall": 0.906064209274673,
        "recurrence_after_feedback": 0.0,
        "regulator_time_cost": 182310.0,
        "repeated_abuse_firms": 10.0,
        "screening_conditioned_precision": 0.9986893840104849,
        "screening_conditioned_recall": 0.906064209274673,
        "severity_weighted_detection_recall": 0.5315331072325047,
        "severity_weighted_greenwashing": 255.09968280861105,
        "sme_burden": 3236.9826225385987,
        "specificity": 0.9791666666666666,
        "state_policy_cost": 117600.0,
        "strategic_material_overstatements": 1168.0,
        "strategic_share_of_material": 0.6689576174112256,
        "subsidy_misallocation": 152998.39489343527,
        "time_to_correction_mean": 9.285714285714286,
        "true_material_overstatements": 1746.0,
        "true_negatives": 47.0,
        "true_positives": 762.0,
        "turnover_replacement_cost": 5028824.177295288,
        "uncommunicated_real_performance": 0.0,
        "unresolved_uncertainty": 62.0,
        "unsupported_generic_claims": 443.0,
        "voluntary_claims_published": 1579.0,
        "voluntary_reporting_declines": 0.0,
        "withheld_truthful_claims": 0.0
      },
      "regime": "certified_green_data_connector",
      "replication": 1,
      "supervision_seed": 950480
    },
    {
      "market_seed": 28262716,
      "metrics": {
        "backlog_pending_cases": 581.0,
        "bank_benefit_misallocation": 0.0,
        "benefit_before_detection": 104733.35979982518,
        "calculation_greenwashing": 465.0,
        "case_completion_days_mean": 265.5081433224756,
        "conflict_cases_opened": 6.0,
        "conflict_claim_corrected": 0.0,
        "conflict_confirmed_firm_claim": 0.0,
        "conflict_dismissed_unresolved": 0.0,
        "conflict_escalated_corroborated": 0.0,
        "conflict_investigations": 6.0,
        "conflict_pending_unresolved": 0.0,
        "conflict_register_corrected": 6.0,
        "conflict_resolution_delay_mean": 51.0,
        "connector_active_source_share": 0.0,
        "consumer_exposure": 1290.0,
        "consumer_perceived_misallocation": 0.11300592305413548,
        "corrected_material_claims": 25.0,
        "correction_delay_days": 357.73127753303964,
        "cost_per_detected_material_claim": 237.88787483702737,
        "cost_per_prevented_material_claim": 0.0,
        "detection_coverage": 0.3952738990332975,
        "detection_delay_days": 0.0,
        "discount_rate_annual": 0.02417932519702056,
        "discounted_exposure_weighted_severity": 235508.81145524053,
        "discounted_total_public_cost": 171158.49238426826,
        "employee_trust_mean": 0.4420134566676367,
        "evidence_quality_mean": 0.21322075399023246,
        "exposure_weighted_severity": 247343.08583529078,
        "false_negatives": 85.0,
        "false_positive_rate_assessed": 0.0,
        "false_positives": 0.0,
        "firm_policy_cost": 0.0,
        "firm_reporting_cost": 6275.464175774061,
        "foregone_consumer_premium": 0.0,
        "green_welfare_share": 0.23767234988030642,
        "gross_emissions_final": 4070088.331018937,
        "hub_participation_rate": 0.0,
        "hub_tot_meaningful_revision_rate": 0.0,
        "hub_tot_revision_rate_adaptive": 0.0,
        "hub_tot_revision_rate_greenwasher": 0.0,
        "hub_tot_revision_rate_honest": 0.0,
        "investor_exposure": 1277.0,
        "investor_signal_distortion": 0.12665822962518528,
        "live_uncorrected_material_overstatements": 1856.0,
        "manual_overrides": 0.0,
        "mean_days_to_correction": 357.73127753303964,
        "mean_greenhushing_gap": 0.0,
        "mean_reporting_delay_days": 0.0,
        "misleading_claim_days": 1672225.0,
        "noise_only_overstatements": 615.0,
        "original_material_overstatements": 1862.0,
        "population_detection_recall": 0.34962406015037595,
        "precision": 1.0,
        "prepublication_meaningful_revisions": 0.0,
        "prepublication_noise_flag_share": 0.0,
        "prepublication_revisions": 0.0,
        "prepublication_withheld_overstatements": 0.0,
        "privacy_cyber_incidents": 0.0,
        "published_claims": 2620.0,
        "queue_mean_age_days": 823.3390705679863,
        "queue_tail_age_days_p90": 1640.0,
        "real_environmental_investment": 272732.4515662845,
        "recall": 0.9002347417840375,
        "recurrence_after_feedback": 0.0,
        "regulator_time_cost": 182460.0,
        "repeated_abuse_firms": 10.0,
        "screening_conditioned_precision": 1.0,
        "screening_conditioned_recall": 0.9002347417840375,
        "severity_weighted_detection_recall": 0.5131978047721387,
        "severity_weighted_greenwashing": 270.7819564595921,
        "sme_burden": 2608.54387955328,
        "specificity": 1.0,
        "state_policy_cost": 0.0,
        "strategic_material_overstatements": 1247.0,
        "strategic_share_of_material": 0.6697099892588615,
        "subsidy_misallocation": 151989.71722743523,
        "time_to_correction_mean": 5.0,
        "true_material_overstatements": 1862.0,
        "true_negatives": 36.0,
        "true_positives": 767.0,
        "turnover_replacement_cost": 4929918.549897284,
        "uncommunicated_real_performance": 0.0,
        "unresolved_uncertainty": 55.0,
        "unsupported_generic_claims": 438.0,
        "voluntary_claims_published": 1594.0,
        "voluntary_reporting_declines": 0.0,
        "withheld_truthful_claims": 0.0
      },
      "regime": "current_eu_supervision",
      "replication": 2,
      "supervision_seed": 958399
    },
    {
      "market_seed": 28262716,
      "metrics": {
        "backlog_pending_cases": 566.0,
        "bank_benefit_misallocation": 0.0,
        "benefit_before_detection": 104568.91149332028,
        "calculation_greenwashing": 465.0,
        "case_completion_days_mean": 256.48447204968943,
        "conflict_cases_opened": 3.0,
        "conflict_claim_corrected": 0.0,
        "conflict_confirmed_firm_claim": 0.0,
        "conflict_dismissed_unresolved": 0.0,
        "conflict_escalated_corroborated": 0.0,
        "conflict_investigations": 3.0,
        "conflict_pending_unresolved": 0.0,
        "conflict_register_corrected": 3.0,
        "conflict_resolution_delay_mean": 51.0,
        "connector_active_source_share": 0.0,
        "consumer_exposure": 1280.0,
        "consumer_perceived_misallocation": 0.10905458647876841,
        "corrected_material_claims": 27.0,
        "correction_delay_days": 349.3008474576271,
        "cost_per_detected_material_claim": 281.3129973474801,
        "cost_per_prevented_material_claim": 477.93333333333334,
        "detection_coverage": 0.38771071234366505,
        "detection_delay_days": 1.1920529801324504,
        "discount_rate_annual": 0.02417932519702056,
        "discounted_exposure_weighted_severity": 231294.88377180859,
        "discounted_total_public_cost": 200405.05675228505,
        "employee_trust_mean": 0.41362434508512363,
        "evidence_quality_mean": 0.21322236082891022,
        "exposure_weighted_severity": 242907.88519733338,
        "false_negatives": 80.0,
        "false_positive_rate_assessed": 0.018518518518518517,
        "false_positives": 1.0,
        "firm_policy_cost": 6645.0,
        "firm_reporting_cost": 6283.812203007278,
        "foregone_consumer_premium": 1339.772266807991,
        "green_welfare_share": 0.2502913551733816,
        "gross_emissions_final": 4035796.9371804665,
        "hub_participation_rate": 0.20833333333333334,
        "hub_tot_meaningful_revision_rate": 0.638095238095238,
        "hub_tot_revision_rate_adaptive": 0.5714285714285714,
        "hub_tot_revision_rate_greenwasher": 0.14285714285714285,
        "hub_tot_revision_rate_honest": 0.8253968253968254,
        "investor_exposure": 1264.0,
        "investor_signal_distortion": 0.12951418598675707,
        "live_uncorrected_material_overstatements": 1830.0,
        "manual_overrides": 0.0,
        "mean_days_to_correction": 349.3008474576271,
        "mean_greenhushing_gap": 0.002679544533615982,
        "mean_reporting_delay_days": 4.0,
        "misleading_claim_days": 1648215.0,
        "noise_only_overstatements": 607.0,
        "original_material_overstatements": 1839.0,
        "population_detection_recall": 0.3442088091353997,
        "precision": 0.9986754966887417,
        "prepublication_meaningful_revisions": 67.0,
        "prepublication_noise_flag_share": 0.0,
        "prepublication_revisions": 67.0,
        "prepublication_withheld_overstatements": 8.0,
        "privacy_cyber_incidents": 0.0,
        "published_claims": 2603.0,
        "queue_mean_age_days": 805.8303886925795,
        "queue_tail_age_days_p90": 1640.0,
        "real_environmental_investment": 284058.9963903683,
        "recall": 0.9040767386091128,
        "recurrence_after_feedback": 214.0,
        "regulator_time_cost": 182910.0,
        "repeated_abuse_firms": 10.0,
        "screening_conditioned_precision": 0.9986754966887417,
        "screening_conditioned_recall": 0.9040767386091128,
        "severity_weighted_detection_recall": 0.506791204660321,
        "severity_weighted_greenwashing": 265.7450088428071,
        "sme_burden": 9260.77746041903,
        "specificity": 0.9814814814814815,
        "state_policy_cost": 29200.0,
        "strategic_material_overstatements": 1232.0,
        "strategic_share_of_material": 0.6699293094072866,
        "subsidy_misallocation": 155416.86776708526,
        "time_to_correction_mean": 5.0,
        "true_material_overstatements": 1839.0,
        "true_negatives": 53.0,
        "true_positives": 754.0,
        "turnover_replacement_cost": 5064432.965344634,
        "uncommunicated_real_performance": 0.002679544533615982,
        "unresolved_uncertainty": 52.0,
        "unsupported_generic_claims": 415.0,
        "voluntary_claims_published": 1577.0,
        "voluntary_reporting_declines": 57.0,
        "withheld_truthful_claims": 4.0
      },
      "regime": "sme_algorithmic_prescreening",
      "replication": 2,
      "supervision_seed": 958399
    },
    {
      "market_seed": 28262716,
      "metrics": {
        "backlog_pending_cases": 593.0,
        "bank_benefit_misallocation": 0.0,
        "benefit_before_detection": 107481.84912148988,
        "calculation_greenwashing": 337.0,
        "case_completion_days_mean": 222.64406779661016,
        "conflict_cases_opened": 6.0,
        "conflict_claim_corrected": 0.0,
        "conflict_confirmed_firm_claim": 0.0,
        "conflict_dismissed_unresolved": 2.0,
        "conflict_escalated_corroborated": 0.0,
        "conflict_investigations": 6.0,
        "conflict_pending_unresolved": 0.0,
        "conflict_register_corrected": 4.0,
        "conflict_resolution_delay_mean": 64.16666666666667,
        "connector_active_source_share": 0.7125,
        "consumer_exposure": 1138.0,
        "consumer_perceived_misallocation": 0.08684674127094864,
        "corrected_material_claims": 21.0,
        "correction_delay_days": 290.2,
        "cost_per_detected_material_claim": 385.18613607188706,
        "cost_per_prevented_material_claim": 119100.0,
        "detection_coverage": 0.42686567164179107,
        "detection_delay_days": 0.0,
        "discount_rate_annual": 0.02417932519702056,
        "discounted_exposure_weighted_severity": 216939.79473487294,
        "discounted_total_public_cost": 284918.21268114005,
        "employee_trust_mean": 0.4432969892721951,
        "evidence_quality_mean": 0.2132226873028752,
        "exposure_weighted_severity": 227646.5923666173,
        "false_negatives": 72.0,
        "false_positive_rate_assessed": 0.0,
        "false_positives": 0.0,
        "firm_policy_cost": 1500.0,
        "firm_reporting_cost": 6297.809167902153,
        "foregone_consumer_premium": 0.0,
        "green_welfare_share": 0.23630537135930577,
        "gross_emissions_final": 4073678.6580809457,
        "hub_participation_rate": 0.0,
        "hub_tot_meaningful_revision_rate": 0.0,
        "hub_tot_revision_rate_adaptive": 0.0,
        "hub_tot_revision_rate_greenwasher": 0.0,
        "hub_tot_revision_rate_honest": 0.0,
        "investor_exposure": 1114.0,
        "investor_signal_distortion": 0.1327048080061715,
        "live_uncorrected_material_overstatements": 1671.0,
        "manual_overrides": 62.0,
        "mean_days_to_correction": 290.2,
        "mean_greenhushing_gap": 0.0,
        "mean_reporting_delay_days": 0.0,
        "misleading_claim_days": 1507745.0,
        "noise_only_overstatements": 554.0,
        "original_material_overstatements": 1675.0,
        "population_detection_recall": 0.3838805970149254,
        "precision": 1.0,
        "prepublication_meaningful_revisions": 0.0,
        "prepublication_noise_flag_share": 0.0,
        "prepublication_revisions": 0.0,
        "prepublication_withheld_overstatements": 0.0,
        "privacy_cyber_incidents": 13.200000000000001,
        "published_claims": 2593.0,
        "queue_mean_age_days": 863.035413153457,
        "queue_tail_age_days_p90": 1760.0,
        "real_environmental_investment": 298522.72124412726,
        "recall": 0.9153936545240893,
        "recurrence_after_feedback": 0.0,
        "regulator_time_cost": 182460.0,
        "repeated_abuse_firms": 10.0,
        "screening_conditioned_precision": 1.0,
        "screening_conditioned_recall": 0.9153936545240893,
        "severity_weighted_detection_recall": 0.5492119106857941,
        "severity_weighted_greenwashing": 248.1936492044302,
        "sme_burden": 3222.6212259592285,
        "specificity": 1.0,
        "state_policy_cost": 117600.0,
        "strategic_material_overstatements": 1121.0,
        "strategic_share_of_material": 0.6692537313432836,
        "subsidy_misallocation": 159245.61699687652,
        "time_to_correction_mean": 5.0,
        "true_material_overstatements": 1675.0,
        "true_negatives": 37.0,
        "true_positives": 779.0,
        "turnover_replacement_cost": 4946770.631094351,
        "uncommunicated_real_performance": 0.0,
        "unresolved_uncertainty": 50.0,
        "unsupported_generic_claims": 432.0,
        "voluntary_claims_published": 1567.0,
        "voluntary_reporting_declines": 0.0,
        "withheld_truthful_claims": 0.0
      },
      "regime": "certified_green_data_connector",
      "replication": 2,
      "supervision_seed": 958399
    }
  ],
  "sample": {
    "affected_revenue_rate": 0.022928432185429743,
    "benefit_multiplier": 1.8615379889688093,
    "compliance_burden_scale": 0.41219442532686873,
    "conflict_capacity_share": 0.43245470575604084,
    "conflict_resolution_days": 51.45713056283688,
    "connector_correction_delay_days": 50.37938469651811,
    "connector_coverage_scale": 0.5235146687812813,
    "connector_downtime_probability": 0.03580678529528183,
    "connector_mismatch_probability": 0.015166922884905815,
    "connector_register_error_probability": 0.011402655360681267,
    "connector_stale_probability": 0.16514853373911184,
    "consumer_discrepancy_sensitivity": 2.106621861003224,
    "consumer_preference_scale": 0.5500632651442808,
    "correction_window_days": 10.99111622501056,
    "evidence_request_capacity": 37.162875684863046,
    "hub_noise": 0.019433910844669368,
    "hub_participation_scale": 0.4752280252481006,
    "hub_processing_delay_days": 3.9286457946537396,
    "hub_strictness": 0.8745074539646495,
    "investigation_capacity": 7.950627502683451,
    "investor_controversy_scale": 0.6808125687996067,
    "investor_sophisticated_fraction": 0.3837095200543887,
    "random_surveillance_share": 0.2978858257965305,
    "regulatory_strictness": 0.6494843575802021,
    "sim_turnover_balance_multiple": 0.8313573522084399,
    "social_discount_rate": 0.02417932519702056,
    "workforce_trust_loss_rate": 0.6476158579523461,
    "workforce_trust_recovery_rate": 0.002214428569234631
  }
}