{
  "code_version": "1645f3589408503894c7e8f44a92ffe382a9a5b4+dirty",
  "complete": true,
  "discount_rate": 0.01586538627111178,
  "draw": 145,
  "horizon_days": 120,
  "regimes": [
    "current_eu_supervision",
    "sme_algorithmic_prescreening",
    "certified_green_data_connector"
  ],
  "replications": 3,
  "rows": [
    {
      "market_seed": 165260716,
      "metrics": {
        "backlog_pending_cases": 9.0,
        "bank_benefit_misallocation": 0.0,
        "benefit_before_detection": 3849.859343680747,
        "calculation_greenwashing": 0.0,
        "case_completion_days_mean": 2.111111111111111,
        "conflict_cases_opened": 0.0,
        "conflict_claim_corrected": 0.0,
        "conflict_confirmed_firm_claim": 0.0,
        "conflict_dismissed_unresolved": 0.0,
        "conflict_escalated_corroborated": 0.0,
        "conflict_investigations": 0.0,
        "conflict_pending_unresolved": 0.0,
        "conflict_register_corrected": 0.0,
        "conflict_resolution_delay_mean": 0.0,
        "connector_active_source_share": 0.0,
        "consumer_exposure": 10.0,
        "consumer_perceived_misallocation": 0.014291848426721042,
        "corrected_material_claims": 0.0,
        "correction_delay_days": 2.111111111111111,
        "cost_per_detected_material_claim": 357.3333333333333,
        "cost_per_prevented_material_claim": 0.0,
        "detection_coverage": 0.43478260869565216,
        "detection_delay_days": 0.0,
        "discount_rate_annual": 0.01586538627111178,
        "discounted_exposure_weighted_severity": 202.12205561840983,
        "discounted_total_public_cost": 5339.240996439427,
        "employee_trust_mean": 0.780548670363965,
        "evidence_quality_mean": 0.5303595744760107,
        "exposure_weighted_severity": 202.64573102086595,
        "false_negatives": 0.0,
        "false_positive_rate_assessed": 0.0,
        "false_positives": 0.0,
        "firm_policy_cost": 0.0,
        "firm_reporting_cost": 323.4191204725033,
        "foregone_consumer_premium": 2236.5385062220557,
        "green_welfare_share": 0.4028993814054271,
        "gross_emissions_final": 3559037.9697837494,
        "hub_participation_rate": 0.0,
        "hub_tot_meaningful_revision_rate": 0.0,
        "hub_tot_revision_rate_adaptive": 0.0,
        "hub_tot_revision_rate_greenwasher": 0.0,
        "hub_tot_revision_rate_honest": 0.0,
        "investor_exposure": 13.0,
        "investor_signal_distortion": 0.05641671560997915,
        "live_uncorrected_material_overstatements": 23.0,
        "manual_overrides": 0.0,
        "mean_days_to_correction": 2.111111111111111,
        "mean_greenhushing_gap": 0.07455128354073519,
        "mean_reporting_delay_days": 0.0,
        "misleading_claim_days": 1080.0,
        "noise_only_overstatements": 3.0,
        "original_material_overstatements": 23.0,
        "population_detection_recall": 0.43478260869565216,
        "precision": 1.0,
        "prepublication_meaningful_revisions": 0.0,
        "prepublication_noise_flag_share": 0.0,
        "prepublication_revisions": 0.0,
        "prepublication_withheld_overstatements": 0.0,
        "privacy_cyber_incidents": 0.0,
        "published_claims": 46.0,
        "queue_mean_age_days": 26.666666666666668,
        "queue_tail_age_days_p90": 60.0,
        "real_environmental_investment": 4829.572962323768,
        "recall": 1.0,
        "recurrence_after_feedback": 0.0,
        "regulator_time_cost": 5360.0,
        "repeated_abuse_firms": 3.0,
        "screening_conditioned_precision": 1.0,
        "screening_conditioned_recall": 1.0,
        "severity_weighted_detection_recall": 0.5546775348107149,
        "severity_weighted_greenwashing": 4.521260853221595,
        "sme_burden": 323.4191204725033,
        "specificity": 1.0,
        "state_policy_cost": 0.0,
        "strategic_material_overstatements": 20.0,
        "strategic_share_of_material": 0.8695652173913043,
        "subsidy_misallocation": 5641.665355159198,
        "time_to_correction_mean": 0.0,
        "true_material_overstatements": 23.0,
        "true_negatives": 3.0,
        "true_positives": 15.0,
        "turnover_replacement_cost": 196463.75838719954,
        "uncommunicated_real_performance": 0.07455128354073519,
        "unresolved_uncertainty": 0.0,
        "unsupported_generic_claims": 13.0,
        "voluntary_claims_published": 46.0,
        "voluntary_reporting_declines": 0.0,
        "withheld_truthful_claims": 0.0
      },
      "regime": "current_eu_supervision",
      "replication": 0,
      "supervision_seed": 15290434
    },
    {
      "market_seed": 165260716,
      "metrics": {
        "backlog_pending_cases": 8.0,
        "bank_benefit_misallocation": 0.0,
        "benefit_before_detection": 3799.428768637642,
        "calculation_greenwashing": 0.0,
        "case_completion_days_mean": 7.9,
        "conflict_cases_opened": 0.0,
        "conflict_claim_corrected": 0.0,
        "conflict_confirmed_firm_claim": 0.0,
        "conflict_dismissed_unresolved": 0.0,
        "conflict_escalated_corroborated": 0.0,
        "conflict_investigations": 0.0,
        "conflict_pending_unresolved": 0.0,
        "conflict_register_corrected": 0.0,
        "conflict_resolution_delay_mean": 0.0,
        "connector_active_source_share": 0.0,
        "consumer_exposure": 9.0,
        "consumer_perceived_misallocation": 0.011740217347056513,
        "corrected_material_claims": 0.0,
        "correction_delay_days": 8.777777777777779,
        "cost_per_detected_material_claim": 2072.0,
        "cost_per_prevented_material_claim": 2230.8333333333335,
        "detection_coverage": 0.5263157894736842,
        "detection_delay_days": 0.0,
        "discount_rate_annual": 0.01586538627111178,
        "discounted_exposure_weighted_severity": 162.60800125635063,
        "discounted_total_public_cost": 30992.053883848712,
        "employee_trust_mean": 0.7837484032129619,
        "evidence_quality_mean": 0.5303595744760107,
        "exposure_weighted_severity": 163.02930020979719,
        "false_negatives": 0.0,
        "false_positive_rate_assessed": 0.0,
        "false_positives": 0.0,
        "firm_policy_cost": 1050.0,
        "firm_reporting_cost": 323.2641362965825,
        "foregone_consumer_premium": 2361.7339084842743,
        "green_welfare_share": 0.40270276387894716,
        "gross_emissions_final": 3559034.177295371,
        "hub_participation_rate": 0.6666666666666666,
        "hub_tot_meaningful_revision_rate": 0.5555555555555556,
        "hub_tot_revision_rate_adaptive": 0.25,
        "hub_tot_revision_rate_greenwasher": 0.0,
        "hub_tot_revision_rate_honest": 0.6428571428571429,
        "investor_exposure": 10.0,
        "investor_signal_distortion": 0.0564163418337317,
        "live_uncorrected_material_overstatements": 19.0,
        "manual_overrides": 0.0,
        "mean_days_to_correction": 8.777777777777779,
        "mean_greenhushing_gap": 0.07872446361614248,
        "mean_reporting_delay_days": 5.0,
        "misleading_claim_days": 840.0,
        "noise_only_overstatements": 1.0,
        "original_material_overstatements": 19.0,
        "population_detection_recall": 0.5263157894736842,
        "precision": 1.0,
        "prepublication_meaningful_revisions": 10.0,
        "prepublication_noise_flag_share": 0.0,
        "prepublication_revisions": 10.0,
        "prepublication_withheld_overstatements": 2.0,
        "privacy_cyber_incidents": 0.0,
        "published_claims": 38.0,
        "queue_mean_age_days": 22.5,
        "queue_tail_age_days_p90": 60.0,
        "real_environmental_investment": 4826.450705800269,
        "recall": 1.0,
        "recurrence_after_feedback": 32.0,
        "regulator_time_cost": 5360.0,
        "repeated_abuse_firms": 2.0,
        "screening_conditioned_precision": 1.0,
        "screening_conditioned_recall": 1.0,
        "severity_weighted_detection_recall": 0.6379678824975893,
        "severity_weighted_greenwashing": 3.8462717138506877,
        "sme_burden": 1373.2641362965824,
        "specificity": 1.0,
        "state_policy_cost": 25720.0,
        "strategic_material_overstatements": 18.0,
        "strategic_share_of_material": 0.9473684210526315,
        "subsidy_misallocation": 5641.627977575568,
        "time_to_correction_mean": 0.0,
        "true_material_overstatements": 19.0,
        "true_negatives": 3.0,
        "true_positives": 15.0,
        "turnover_replacement_cost": 196211.52809292127,
        "uncommunicated_real_performance": 0.07872446361614248,
        "unresolved_uncertainty": 0.0,
        "unsupported_generic_claims": 9.0,
        "voluntary_claims_published": 38.0,
        "voluntary_reporting_declines": 2.0,
        "withheld_truthful_claims": 3.0
      },
      "regime": "sme_algorithmic_prescreening",
      "replication": 0,
      "supervision_seed": 15290434
    },
    {
      "market_seed": 165260716,
      "metrics": {
        "backlog_pending_cases": 8.0,
        "bank_benefit_misallocation": 0.0,
        "benefit_before_detection": 3350.0133525557317,
        "calculation_greenwashing": 0.0,
        "case_completion_days_mean": 1.9,
        "conflict_cases_opened": 0.0,
        "conflict_claim_corrected": 0.0,
        "conflict_confirmed_firm_claim": 0.0,
        "conflict_dismissed_unresolved": 0.0,
        "conflict_escalated_corroborated": 0.0,
        "conflict_investigations": 0.0,
        "conflict_pending_unresolved": 0.0,
        "conflict_register_corrected": 0.0,
        "conflict_resolution_delay_mean": 0.0,
        "connector_active_source_share": 0.7,
        "consumer_exposure": 11.0,
        "consumer_perceived_misallocation": 0.02101961782418151,
        "corrected_material_claims": 0.0,
        "correction_delay_days": 2.111111111111111,
        "cost_per_detected_material_claim": 5011.428571428572,
        "cost_per_prevented_material_claim": 66300.0,
        "detection_coverage": 0.37037037037037035,
        "detection_delay_days": 0.0,
        "discount_rate_annual": 0.01586538627111178,
        "discounted_exposure_weighted_severity": 216.22721918984666,
        "discounted_total_public_cost": 69965.59934605002,
        "employee_trust_mean": 0.7735655720744223,
        "evidence_quality_mean": 0.5303595744760107,
        "exposure_weighted_severity": 216.78743947696353,
        "false_negatives": 0.0,
        "false_positive_rate_assessed": 0.0,
        "false_positives": 0.0,
        "firm_policy_cost": 1500.0,
        "firm_reporting_cost": 325.8580043519768,
        "foregone_consumer_premium": 2236.122275654577,
        "green_welfare_share": 0.3974401196256997,
        "gross_emissions_final": 3565827.4079275005,
        "hub_participation_rate": 0.0,
        "hub_tot_meaningful_revision_rate": 0.0,
        "hub_tot_revision_rate_adaptive": 0.0,
        "hub_tot_revision_rate_greenwasher": 0.0,
        "hub_tot_revision_rate_honest": 0.0,
        "investor_exposure": 16.0,
        "investor_signal_distortion": 0.05690202672788421,
        "live_uncorrected_material_overstatements": 27.0,
        "manual_overrides": 0.0,
        "mean_days_to_correction": 2.111111111111111,
        "mean_greenhushing_gap": 0.0745374091884859,
        "mean_reporting_delay_days": 0.0,
        "misleading_claim_days": 1260.0,
        "noise_only_overstatements": 6.0,
        "original_material_overstatements": 27.0,
        "population_detection_recall": 0.37037037037037035,
        "precision": 1.0,
        "prepublication_meaningful_revisions": 0.0,
        "prepublication_noise_flag_share": 0.0,
        "prepublication_revisions": 0.0,
        "prepublication_withheld_overstatements": 0.0,
        "privacy_cyber_incidents": 0.2,
        "published_claims": 47.0,
        "queue_mean_age_days": 30.0,
        "queue_tail_age_days_p90": 60.0,
        "real_environmental_investment": 4778.683026564814,
        "recall": 1.0,
        "recurrence_after_feedback": 0.0,
        "regulator_time_cost": 5360.0,
        "repeated_abuse_firms": 2.0,
        "screening_conditioned_precision": 1.0,
        "screening_conditioned_recall": 1.0,
        "severity_weighted_detection_recall": 0.5094451361929945,
        "severity_weighted_greenwashing": 4.930750333452306,
        "sme_burden": 1825.858004351977,
        "specificity": 1.0,
        "state_policy_cost": 64800.0,
        "strategic_material_overstatements": 21.0,
        "strategic_share_of_material": 0.7777777777777778,
        "subsidy_misallocation": 5690.197551606016,
        "time_to_correction_mean": 0.0,
        "true_material_overstatements": 27.0,
        "true_negatives": 4.0,
        "true_positives": 14.0,
        "turnover_replacement_cost": 198698.52908508267,
        "uncommunicated_real_performance": 0.0745374091884859,
        "unresolved_uncertainty": 1.0,
        "unsupported_generic_claims": 13.0,
        "voluntary_claims_published": 47.0,
        "voluntary_reporting_declines": 0.0,
        "withheld_truthful_claims": 0.0
      },
      "regime": "certified_green_data_connector",
      "replication": 0,
      "supervision_seed": 15290434
    },
    {
      "market_seed": 165261716,
      "metrics": {
        "backlog_pending_cases": 10.0,
        "bank_benefit_misallocation": 0.0,
        "benefit_before_detection": 3347.947401050431,
        "calculation_greenwashing": 0.0,
        "case_completion_days_mean": 0.0,
        "conflict_cases_opened": 0.0,
        "conflict_claim_corrected": 0.0,
        "conflict_confirmed_firm_claim": 0.0,
        "conflict_dismissed_unresolved": 0.0,
        "conflict_escalated_corroborated": 0.0,
        "conflict_investigations": 0.0,
        "conflict_pending_unresolved": 0.0,
        "conflict_register_corrected": 0.0,
        "conflict_resolution_delay_mean": 0.0,
        "connector_active_source_share": 0.0,
        "consumer_exposure": 11.0,
        "consumer_perceived_misallocation": 0.020446826767841025,
        "corrected_material_claims": 0.0,
        "correction_delay_days": 0.0,
        "cost_per_detected_material_claim": 315.29411764705884,
        "cost_per_prevented_material_claim": 0.0,
        "detection_coverage": 0.48,
        "detection_delay_days": 0.0,
        "discount_rate_annual": 0.01586538627111178,
        "discounted_exposure_weighted_severity": 200.34039796215663,
        "discounted_total_public_cost": 5339.240996439427,
        "employee_trust_mean": 0.7665750975184886,
        "evidence_quality_mean": 0.5303464208958493,
        "exposure_weighted_severity": 200.8594572909867,
        "false_negatives": 0.0,
        "false_positive_rate_assessed": 0.0,
        "false_positives": 0.0,
        "firm_policy_cost": 0.0,
        "firm_reporting_cost": 338.47866474754113,
        "foregone_consumer_premium": 2214.036043751665,
        "green_welfare_share": 0.4093785943622305,
        "gross_emissions_final": 3534245.6566432063,
        "hub_participation_rate": 0.0,
        "hub_tot_meaningful_revision_rate": 0.0,
        "hub_tot_revision_rate_adaptive": 0.0,
        "hub_tot_revision_rate_greenwasher": 0.0,
        "hub_tot_revision_rate_honest": 0.0,
        "investor_exposure": 14.0,
        "investor_signal_distortion": 0.05771528454982361,
        "live_uncorrected_material_overstatements": 25.0,
        "manual_overrides": 0.0,
        "mean_days_to_correction": 0.0,
        "mean_greenhushing_gap": 0.07380120145838884,
        "mean_reporting_delay_days": 0.0,
        "misleading_claim_days": 1020.0,
        "noise_only_overstatements": 5.0,
        "original_material_overstatements": 25.0,
        "population_detection_recall": 0.48,
        "precision": 1.0,
        "prepublication_meaningful_revisions": 0.0,
        "prepublication_noise_flag_share": 0.0,
        "prepublication_revisions": 0.0,
        "prepublication_withheld_overstatements": 0.0,
        "privacy_cyber_incidents": 0.0,
        "published_claims": 49.0,
        "queue_mean_age_days": 30.0,
        "queue_tail_age_days_p90": 60.0,
        "real_environmental_investment": 5432.802683477677,
        "recall": 1.0,
        "recurrence_after_feedback": 0.0,
        "regulator_time_cost": 5360.0,
        "repeated_abuse_firms": 3.0,
        "screening_conditioned_precision": 1.0,
        "screening_conditioned_recall": 1.0,
        "severity_weighted_detection_recall": 0.6224525973240989,
        "severity_weighted_greenwashing": 4.773251814893331,
        "sme_burden": 338.47866474754113,
        "specificity": 1.0,
        "state_policy_cost": 0.0,
        "strategic_material_overstatements": 20.0,
        "strategic_share_of_material": 0.8,
        "subsidy_misallocation": 5771.52210630106,
        "time_to_correction_mean": 0.0,
        "true_material_overstatements": 25.0,
        "true_negatives": 1.0,
        "true_positives": 17.0,
        "turnover_replacement_cost": 197571.70881268405,
        "uncommunicated_real_performance": 0.07380120145838884,
        "unresolved_uncertainty": 0.0,
        "unsupported_generic_claims": 14.0,
        "voluntary_claims_published": 49.0,
        "voluntary_reporting_declines": 0.0,
        "withheld_truthful_claims": 0.0
      },
      "regime": "current_eu_supervision",
      "replication": 1,
      "supervision_seed": 15298353
    },
    {
      "market_seed": 165261716,
      "metrics": {
        "backlog_pending_cases": 9.0,
        "bank_benefit_misallocation": 0.0,
        "benefit_before_detection": 3880.4719035155126,
        "calculation_greenwashing": 0.0,
        "case_completion_days_mean": 0.0,
        "conflict_cases_opened": 0.0,
        "conflict_claim_corrected": 0.0,
        "conflict_confirmed_firm_claim": 0.0,
        "conflict_dismissed_unresolved": 0.0,
        "conflict_escalated_corroborated": 0.0,
        "conflict_investigations": 0.0,
        "conflict_pending_unresolved": 0.0,
        "conflict_register_corrected": 0.0,
        "conflict_resolution_delay_mean": 0.0,
        "connector_active_source_share": 0.0,
        "consumer_exposure": 9.0,
        "consumer_perceived_misallocation": 0.02158936211482859,
        "corrected_material_claims": 0.0,
        "correction_delay_days": 0.0,
        "cost_per_detected_material_claim": 1828.235294117647,
        "cost_per_prevented_material_claim": 1595.8823529411766,
        "detection_coverage": 0.631578947368421,
        "detection_delay_days": 3.5294117647058822,
        "discount_rate_annual": 0.01586538627111178,
        "discounted_exposure_weighted_severity": 182.76495592067286,
        "discounted_total_public_cost": 30992.053883848712,
        "employee_trust_mean": 0.7837484032129619,
        "evidence_quality_mean": 0.5304040067110807,
        "exposure_weighted_severity": 183.23847926553393,
        "false_negatives": 0.0,
        "false_positive_rate_assessed": 0.0,
        "false_positives": 0.0,
        "firm_policy_cost": 1410.0,
        "firm_reporting_cost": 322.1613784791467,
        "foregone_consumer_premium": 2335.2640714392546,
        "green_welfare_share": 0.3991079371572657,
        "gross_emissions_final": 3570598.3184061795,
        "hub_participation_rate": 0.8333333333333334,
        "hub_tot_meaningful_revision_rate": 0.8888888888888888,
        "hub_tot_revision_rate_adaptive": 0.75,
        "hub_tot_revision_rate_greenwasher": 0.0,
        "hub_tot_revision_rate_honest": 0.9285714285714286,
        "investor_exposure": 10.0,
        "investor_signal_distortion": 0.05954243453699657,
        "live_uncorrected_material_overstatements": 19.0,
        "manual_overrides": 0.0,
        "mean_days_to_correction": 0.0,
        "mean_greenhushing_gap": 0.07784213571464181,
        "mean_reporting_delay_days": 5.0,
        "misleading_claim_days": 840.0,
        "noise_only_overstatements": 3.0,
        "original_material_overstatements": 19.0,
        "population_detection_recall": 0.631578947368421,
        "precision": 1.0,
        "prepublication_meaningful_revisions": 16.0,
        "prepublication_noise_flag_share": 0.0,
        "prepublication_revisions": 16.0,
        "prepublication_withheld_overstatements": 1.0,
        "privacy_cyber_incidents": 0.0,
        "published_claims": 38.0,
        "queue_mean_age_days": 33.333333333333336,
        "queue_tail_age_days_p90": 60.0,
        "real_environmental_investment": 4598.545619604269,
        "recall": 1.0,
        "recurrence_after_feedback": 31.0,
        "regulator_time_cost": 5360.0,
        "repeated_abuse_firms": 2.0,
        "screening_conditioned_precision": 1.0,
        "screening_conditioned_recall": 1.0,
        "severity_weighted_detection_recall": 0.7322662292393306,
        "severity_weighted_greenwashing": 4.048619601095311,
        "sme_burden": 1732.1613784791466,
        "specificity": 1.0,
        "state_policy_cost": 25720.0,
        "strategic_material_overstatements": 16.0,
        "strategic_share_of_material": 0.8421052631578947,
        "subsidy_misallocation": 5954.237499456203,
        "time_to_correction_mean": 0.0,
        "true_material_overstatements": 19.0,
        "true_negatives": 1.0,
        "true_positives": 17.0,
        "turnover_replacement_cost": 192900.357092008,
        "uncommunicated_real_performance": 0.07784213571464181,
        "unresolved_uncertainty": 0.0,
        "unsupported_generic_claims": 8.0,
        "voluntary_claims_published": 38.0,
        "voluntary_reporting_declines": 1.0,
        "withheld_truthful_claims": 0.0
      },
      "regime": "sme_algorithmic_prescreening",
      "replication": 1,
      "supervision_seed": 15298353
    },
    {
      "market_seed": 165261716,
      "metrics": {
        "backlog_pending_cases": 10.0,
        "bank_benefit_misallocation": 0.0,
        "benefit_before_detection": 3135.7625586319355,
        "calculation_greenwashing": 0.0,
        "case_completion_days_mean": 0.0,
        "conflict_cases_opened": 1.0,
        "conflict_claim_corrected": 0.0,
        "conflict_confirmed_firm_claim": 0.0,
        "conflict_dismissed_unresolved": 0.0,
        "conflict_escalated_corroborated": 0.0,
        "conflict_investigations": 1.0,
        "conflict_pending_unresolved": 1.0,
        "conflict_register_corrected": 0.0,
        "conflict_resolution_delay_mean": 0.0,
        "connector_active_source_share": 0.7375,
        "consumer_exposure": 11.0,
        "consumer_perceived_misallocation": 0.020382733959068682,
        "corrected_material_claims": 0.0,
        "correction_delay_days": 0.0,
        "cost_per_detected_material_claim": 4667.333333333333,
        "cost_per_prevented_material_claim": 66300.0,
        "detection_coverage": 0.44,
        "detection_delay_days": 0.0,
        "discount_rate_annual": 0.01586538627111178,
        "discounted_exposure_weighted_severity": 195.1030192522853,
        "discounted_total_public_cost": 69815.98697479488,
        "employee_trust_mean": 0.7735655720744223,
        "evidence_quality_mean": 0.5303464208958493,
        "exposure_weighted_severity": 195.60850912480188,
        "false_negatives": 1.0,
        "false_positive_rate_assessed": 0.0,
        "false_positives": 0.0,
        "firm_policy_cost": 1500.0,
        "firm_reporting_cost": 338.14890477441986,
        "foregone_consumer_premium": 2214.2747528404134,
        "green_welfare_share": 0.410751617037935,
        "gross_emissions_final": 3530573.233475446,
        "hub_participation_rate": 0.0,
        "hub_tot_meaningful_revision_rate": 0.0,
        "hub_tot_revision_rate_adaptive": 0.0,
        "hub_tot_revision_rate_greenwasher": 0.0,
        "hub_tot_revision_rate_honest": 0.0,
        "investor_exposure": 14.0,
        "investor_signal_distortion": 0.05760684864011215,
        "live_uncorrected_material_overstatements": 25.0,
        "manual_overrides": 0.0,
        "mean_days_to_correction": 0.0,
        "mean_greenhushing_gap": 0.07380915842801378,
        "mean_reporting_delay_days": 0.0,
        "misleading_claim_days": 1080.0,
        "noise_only_overstatements": 7.0,
        "original_material_overstatements": 25.0,
        "population_detection_recall": 0.4,
        "precision": 1.0,
        "prepublication_meaningful_revisions": 0.0,
        "prepublication_noise_flag_share": 0.0,
        "prepublication_revisions": 0.0,
        "prepublication_withheld_overstatements": 0.0,
        "privacy_cyber_incidents": 0.0,
        "published_claims": 49.0,
        "queue_mean_age_days": 36.0,
        "queue_tail_age_days_p90": 60.0,
        "real_environmental_investment": 5567.735155819375,
        "recall": 0.9375,
        "recurrence_after_feedback": 0.0,
        "regulator_time_cost": 5210.0,
        "repeated_abuse_firms": 3.0,
        "screening_conditioned_precision": 1.0,
        "screening_conditioned_recall": 0.9375,
        "severity_weighted_detection_recall": 0.5636088454268194,
        "severity_weighted_greenwashing": 4.366828400454019,
        "sme_burden": 1838.1489047744199,
        "specificity": 1.0,
        "state_policy_cost": 64800.0,
        "strategic_material_overstatements": 18.0,
        "strategic_share_of_material": 0.72,
        "subsidy_misallocation": 5760.6785272578645,
        "time_to_correction_mean": 0.0,
        "true_material_overstatements": 25.0,
        "true_negatives": 2.0,
        "true_positives": 15.0,
        "turnover_replacement_cost": 195413.01299706916,
        "uncommunicated_real_performance": 0.07380915842801378,
        "unresolved_uncertainty": 1.0,
        "unsupported_generic_claims": 14.0,
        "voluntary_claims_published": 49.0,
        "voluntary_reporting_declines": 0.0,
        "withheld_truthful_claims": 0.0
      },
      "regime": "certified_green_data_connector",
      "replication": 1,
      "supervision_seed": 15298353
    },
    {
      "market_seed": 165262716,
      "metrics": {
        "backlog_pending_cases": 8.0,
        "bank_benefit_misallocation": 0.0,
        "benefit_before_detection": 3701.888544409663,
        "calculation_greenwashing": 0.0,
        "case_completion_days_mean": 1.9,
        "conflict_cases_opened": 0.0,
        "conflict_claim_corrected": 0.0,
        "conflict_confirmed_firm_claim": 0.0,
        "conflict_dismissed_unresolved": 0.0,
        "conflict_escalated_corroborated": 0.0,
        "conflict_investigations": 0.0,
        "conflict_pending_unresolved": 0.0,
        "conflict_register_corrected": 0.0,
        "conflict_resolution_delay_mean": 0.0,
        "connector_active_source_share": 0.0,
        "consumer_exposure": 9.0,
        "consumer_perceived_misallocation": 0.014231569882468143,
        "corrected_material_claims": 0.0,
        "correction_delay_days": 2.111111111111111,
        "cost_per_detected_material_claim": 357.3333333333333,
        "cost_per_prevented_material_claim": 0.0,
        "detection_coverage": 0.4090909090909091,
        "detection_delay_days": 0.0,
        "discount_rate_annual": 0.01586538627111178,
        "discounted_exposure_weighted_severity": 192.49619562952842,
        "discounted_total_public_cost": 5339.240996439427,
        "employee_trust_mean": 0.780548670363965,
        "evidence_quality_mean": 0.5303586382102083,
        "exposure_weighted_severity": 192.99493151665928,
        "false_negatives": 0.0,
        "false_positive_rate_assessed": 0.0,
        "false_positives": 0.0,
        "firm_policy_cost": 0.0,
        "firm_reporting_cost": 321.5453865469672,
        "foregone_consumer_premium": 2184.5268876791565,
        "green_welfare_share": 0.39361553035741986,
        "gross_emissions_final": 3587920.806436559,
        "hub_participation_rate": 0.0,
        "hub_tot_meaningful_revision_rate": 0.0,
        "hub_tot_revision_rate_adaptive": 0.0,
        "hub_tot_revision_rate_greenwasher": 0.0,
        "hub_tot_revision_rate_honest": 0.0,
        "investor_exposure": 13.0,
        "investor_signal_distortion": 0.061774356984034516,
        "live_uncorrected_material_overstatements": 22.0,
        "manual_overrides": 0.0,
        "mean_days_to_correction": 2.111111111111111,
        "mean_greenhushing_gap": 0.07281756292263854,
        "mean_reporting_delay_days": 0.0,
        "misleading_claim_days": 1020.0,
        "noise_only_overstatements": 3.0,
        "original_material_overstatements": 22.0,
        "population_detection_recall": 0.4090909090909091,
        "precision": 1.0,
        "prepublication_meaningful_revisions": 0.0,
        "prepublication_noise_flag_share": 0.0,
        "prepublication_revisions": 0.0,
        "prepublication_withheld_overstatements": 0.0,
        "privacy_cyber_incidents": 0.0,
        "published_claims": 45.0,
        "queue_mean_age_days": 30.0,
        "queue_tail_age_days_p90": 60.0,
        "real_environmental_investment": 4436.387385644433,
        "recall": 1.0,
        "recurrence_after_feedback": 0.0,
        "regulator_time_cost": 5360.0,
        "repeated_abuse_firms": 3.0,
        "screening_conditioned_precision": 1.0,
        "screening_conditioned_recall": 1.0,
        "severity_weighted_detection_recall": 0.5264104687391428,
        "severity_weighted_greenwashing": 4.355040479385068,
        "sme_burden": 321.5453865469672,
        "specificity": 1.0,
        "state_policy_cost": 0.0,
        "strategic_material_overstatements": 19.0,
        "strategic_share_of_material": 0.8636363636363636,
        "subsidy_misallocation": 6177.430138711324,
        "time_to_correction_mean": 0.0,
        "true_material_overstatements": 22.0,
        "true_negatives": 3.0,
        "true_positives": 15.0,
        "turnover_replacement_cost": 192695.67185598085,
        "uncommunicated_real_performance": 0.07281756292263854,
        "unresolved_uncertainty": 0.0,
        "unsupported_generic_claims": 12.0,
        "voluntary_claims_published": 45.0,
        "voluntary_reporting_declines": 0.0,
        "withheld_truthful_claims": 0.0
      },
      "regime": "current_eu_supervision",
      "replication": 2,
      "supervision_seed": 15306272
    },
    {
      "market_seed": 165262716,
      "metrics": {
        "backlog_pending_cases": 7.0,
        "bank_benefit_misallocation": 0.0,
        "benefit_before_detection": 3747.10940377877,
        "calculation_greenwashing": 0.0,
        "case_completion_days_mean": 1.7272727272727273,
        "conflict_cases_opened": 0.0,
        "conflict_claim_corrected": 0.0,
        "conflict_confirmed_firm_claim": 0.0,
        "conflict_dismissed_unresolved": 0.0,
        "conflict_escalated_corroborated": 0.0,
        "conflict_investigations": 0.0,
        "conflict_pending_unresolved": 0.0,
        "conflict_register_corrected": 0.0,
        "conflict_resolution_delay_mean": 0.0,
        "connector_active_source_share": 0.0,
        "consumer_exposure": 9.0,
        "consumer_perceived_misallocation": 0.016840786567438322,
        "corrected_material_claims": 0.0,
        "correction_delay_days": 2.111111111111111,
        "cost_per_detected_material_claim": 2072.0,
        "cost_per_prevented_material_claim": 1804.6666666666667,
        "detection_coverage": 0.5789473684210527,
        "detection_delay_days": 0.0,
        "discount_rate_annual": 0.01586538627111178,
        "discounted_exposure_weighted_severity": 175.73615253746206,
        "discounted_total_public_cost": 30992.053883848712,
        "employee_trust_mean": 0.7837484032129619,
        "evidence_quality_mean": 0.5303586382102083,
        "exposure_weighted_severity": 176.19146504714618,
        "false_negatives": 1.0,
        "false_positive_rate_assessed": 0.0,
        "false_positives": 0.0,
        "firm_policy_cost": 1350.0,
        "firm_reporting_cost": 321.6084752822925,
        "foregone_consumer_premium": 2528.841058640882,
        "green_welfare_share": 0.3921438370614091,
        "gross_emissions_final": 3587922.70558353,
        "hub_participation_rate": 0.8333333333333334,
        "hub_tot_meaningful_revision_rate": 0.8333333333333334,
        "hub_tot_revision_rate_adaptive": 0.75,
        "hub_tot_revision_rate_greenwasher": 0.0,
        "hub_tot_revision_rate_honest": 0.8571428571428571,
        "investor_exposure": 10.0,
        "investor_signal_distortion": 0.061774547201998584,
        "live_uncorrected_material_overstatements": 19.0,
        "manual_overrides": 0.0,
        "mean_days_to_correction": 2.111111111111111,
        "mean_greenhushing_gap": 0.08429470195469607,
        "mean_reporting_delay_days": 5.0,
        "misleading_claim_days": 900.0,
        "noise_only_overstatements": 1.0,
        "original_material_overstatements": 19.0,
        "population_detection_recall": 0.5263157894736842,
        "precision": 1.0,
        "prepublication_meaningful_revisions": 15.0,
        "prepublication_noise_flag_share": 0.0,
        "prepublication_revisions": 15.0,
        "prepublication_withheld_overstatements": 0.0,
        "privacy_cyber_incidents": 0.0,
        "published_claims": 37.0,
        "queue_mean_age_days": 34.285714285714285,
        "queue_tail_age_days_p90": 60.0,
        "real_environmental_investment": 4437.639418182569,
        "recall": 0.9375,
        "recurrence_after_feedback": 32.0,
        "regulator_time_cost": 5360.0,
        "repeated_abuse_firms": 2.0,
        "screening_conditioned_precision": 1.0,
        "screening_conditioned_recall": 0.9375,
        "severity_weighted_detection_recall": 0.6478852440215693,
        "severity_weighted_greenwashing": 3.890274971488943,
        "sme_burden": 1671.6084752822926,
        "specificity": 1.0,
        "state_policy_cost": 25720.0,
        "strategic_material_overstatements": 18.0,
        "strategic_share_of_material": 0.9473684210526315,
        "subsidy_misallocation": 6177.449160490611,
        "time_to_correction_mean": 0.0,
        "true_material_overstatements": 19.0,
        "true_negatives": 2.0,
        "true_positives": 15.0,
        "turnover_replacement_cost": 192434.3305855678,
        "uncommunicated_real_performance": 0.08429470195469607,
        "unresolved_uncertainty": 0.0,
        "unsupported_generic_claims": 8.0,
        "voluntary_claims_published": 37.0,
        "voluntary_reporting_declines": 1.0,
        "withheld_truthful_claims": 2.0
      },
      "regime": "sme_algorithmic_prescreening",
      "replication": 2,
      "supervision_seed": 15306272
    },
    {
      "market_seed": 165262716,
      "metrics": {
        "backlog_pending_cases": 8.0,
        "bank_benefit_misallocation": 0.0,
        "benefit_before_detection": 2606.486270007015,
        "calculation_greenwashing": 0.0,
        "case_completion_days_mean": 1.9,
        "conflict_cases_opened": 1.0,
        "conflict_claim_corrected": 0.0,
        "conflict_confirmed_firm_claim": 0.0,
        "conflict_dismissed_unresolved": 0.0,
        "conflict_escalated_corroborated": 0.0,
        "conflict_investigations": 1.0,
        "conflict_pending_unresolved": 1.0,
        "conflict_register_corrected": 0.0,
        "conflict_resolution_delay_mean": 0.0,
        "connector_active_source_share": 0.6875,
        "consumer_exposure": 12.0,
        "consumer_perceived_misallocation": 0.025190494622728717,
        "corrected_material_claims": 0.0,
        "correction_delay_days": 2.375,
        "cost_per_detected_material_claim": 5000.714285714285,
        "cost_per_prevented_material_claim": 66300.0,
        "detection_coverage": 0.42857142857142855,
        "detection_delay_days": 0.0,
        "discount_rate_annual": 0.01586538627111178,
        "discounted_exposure_weighted_severity": 234.8605744193812,
        "discounted_total_public_cost": 69815.98697479488,
        "employee_trust_mean": 0.780540889214473,
        "evidence_quality_mean": 0.5303586382102083,
        "exposure_weighted_severity": 235.46907162397292,
        "false_negatives": 1.0,
        "false_positive_rate_assessed": 0.0,
        "false_positives": 0.0,
        "firm_policy_cost": 1500.0,
        "firm_reporting_cost": 324.34050750264487,
        "foregone_consumer_premium": 2184.9304176027667,
        "green_welfare_share": 0.3917166034416205,
        "gross_emissions_final": 3581520.5520053892,
        "hub_participation_rate": 0.0,
        "hub_tot_meaningful_revision_rate": 0.0,
        "hub_tot_revision_rate_adaptive": 0.0,
        "hub_tot_revision_rate_greenwasher": 0.0,
        "hub_tot_revision_rate_honest": 0.0,
        "investor_exposure": 16.0,
        "investor_signal_distortion": 0.06081338173692452,
        "live_uncorrected_material_overstatements": 28.0,
        "manual_overrides": 0.0,
        "mean_days_to_correction": 2.375,
        "mean_greenhushing_gap": 0.07283101392009222,
        "mean_reporting_delay_days": 0.0,
        "misleading_claim_days": 1260.0,
        "noise_only_overstatements": 6.0,
        "original_material_overstatements": 28.0,
        "population_detection_recall": 0.39285714285714285,
        "precision": 1.0,
        "prepublication_meaningful_revisions": 0.0,
        "prepublication_noise_flag_share": 0.0,
        "prepublication_revisions": 0.0,
        "prepublication_withheld_overstatements": 0.0,
        "privacy_cyber_incidents": 1.2,
        "published_claims": 48.0,
        "queue_mean_age_days": 37.5,
        "queue_tail_age_days_p90": 60.0,
        "real_environmental_investment": 4624.5484881686125,
        "recall": 0.9333333333333333,
        "recurrence_after_feedback": 0.0,
        "regulator_time_cost": 5210.0,
        "repeated_abuse_firms": 3.0,
        "screening_conditioned_precision": 1.0,
        "screening_conditioned_recall": 0.9333333333333333,
        "severity_weighted_detection_recall": 0.5325138211199533,
        "severity_weighted_greenwashing": 5.208319680336032,
        "sme_burden": 1824.3405075026449,
        "specificity": 1.0,
        "state_policy_cost": 64800.0,
        "strategic_material_overstatements": 22.0,
        "strategic_share_of_material": 0.7857142857142857,
        "subsidy_misallocation": 6081.332092354278,
        "time_to_correction_mean": 0.0,
        "true_material_overstatements": 28.0,
        "true_negatives": 3.0,
        "true_positives": 14.0,
        "turnover_replacement_cost": 192540.7835632634,
        "uncommunicated_real_performance": 0.07283101392009222,
        "unresolved_uncertainty": 2.0,
        "unsupported_generic_claims": 13.0,
        "voluntary_claims_published": 48.0,
        "voluntary_reporting_declines": 0.0,
        "withheld_truthful_claims": 0.0
      },
      "regime": "certified_green_data_connector",
      "replication": 2,
      "supervision_seed": 15306272
    }
  ],
  "sample": {
    "affected_revenue_rate": 0.04432323078696248,
    "benefit_multiplier": 2.184866244529033,
    "compliance_burden_scale": 0.9731610152826091,
    "conflict_capacity_share": 0.4305814263950426,
    "conflict_resolution_days": 23.166609205883727,
    "connector_correction_delay_days": 109.73181286894726,
    "connector_coverage_scale": 0.828001225934943,
    "connector_downtime_probability": 0.0042489191592265125,
    "connector_mismatch_probability": 0.0963412604523307,
    "connector_register_error_probability": 0.04290993091783418,
    "connector_stale_probability": 0.18810640512103904,
    "consumer_discrepancy_sensitivity": 0.27612684031463935,
    "consumer_preference_scale": 1.2792102415331477,
    "correction_window_days": 38.70152849849835,
    "evidence_request_capacity": 8.579044181513284,
    "hub_noise": 0.3873275874627641,
    "hub_participation_scale": 1.331363463467048,
    "hub_processing_delay_days": 5.03351285745412,
    "hub_strictness": 0.6920710421946816,
    "investigation_capacity": 4.370191247380575,
    "investor_controversy_scale": 1.5328835986074687,
    "investor_sophisticated_fraction": 0.1368754731920217,
    "random_surveillance_share": 0.10306882995981798,
    "regulatory_strictness": 0.9460836423460414,
    "sim_turnover_balance_multiple": 0.6469623819427756,
    "social_discount_rate": 0.01586538627111178,
    "workforce_trust_loss_rate": 0.697305413013813,
    "workforce_trust_recovery_rate": 0.004750076544928834
  }
}